circuit_breaker.py
config.py
pyhystrix.py
version.py
pyhystrix-1.0.0.dist-info/LICENSE
pyhystrix-1.0.0.dist-info/METADATA
pyhystrix-1.0.0.dist-info/WHEEL
pyhystrix-1.0.0.dist-info/top_level.txt
pyhystrix-1.0.0.dist-info/RECORD
