Metadata-Version: 2.1
Name: pyhystrix
Version: 1.0.0
Summary: UNKNOWN
Home-page: https://github.com/oogway/pyhystrix
Author: Mohan Dutt
Author-email: mohan@oogway.in
License: UNKNOWN
Platform: UNKNOWN
Requires-Dist: certifi (==2017.4.17)
Requires-Dist: chardet (==3.0.4)
Requires-Dist: httmock (==1.2.6)
Requires-Dist: idna (==2.5)
Requires-Dist: requests (==2.22.0)
Requires-Dist: urllib3 (==1.25.6)
